FlowCyPy/__init__.py
FlowCyPy/_version.py
FlowCyPy/analyzer.py
FlowCyPy/cytometer.py
FlowCyPy/detector.py
FlowCyPy/directories.py
FlowCyPy/flow_cell.py
FlowCyPy/helper.py
FlowCyPy/logger.py
FlowCyPy/noises.py
FlowCyPy/physical_constant.py
FlowCyPy/population.py
FlowCyPy/populations_instances.py
FlowCyPy/report.py
FlowCyPy/scatterer.py
FlowCyPy/source.py
FlowCyPy/units.py
FlowCyPy/utils.py
FlowCyPy/coupling_mechanism/__init__.py
FlowCyPy/coupling_mechanism/empirical.py
FlowCyPy/coupling_mechanism/mie.py
FlowCyPy/coupling_mechanism/rayleigh.py
FlowCyPy/coupling_mechanism/uniform.py
FlowCyPy/distribution/__init__.py
FlowCyPy/distribution/base_class.py
FlowCyPy/distribution/delta.py
FlowCyPy/distribution/lognormal.py
FlowCyPy/distribution/normal.py
FlowCyPy/distribution/particle_size_distribution.py
FlowCyPy/distribution/uniform.py
FlowCyPy/distribution/weibull.py
FlowCyPy/peak_locator/__init__.py
FlowCyPy/peak_locator/base_class.py
FlowCyPy/peak_locator/basic.py
FlowCyPy/peak_locator/moving_average.py
FlowCyPy-1.3.2.dist-info/LICENSE
FlowCyPy-1.3.2.dist-info/METADATA
FlowCyPy-1.3.2.dist-info/WHEEL
FlowCyPy-1.3.2.dist-info/top_level.txt
FlowCyPy-1.3.2.dist-info/RECORD
