Metadata-Version: 2.1
Name: FlowCyPy
Version: 1.3.2
Summary: A package for flow-cytometry simulations.
Author-email: Martin Poinsinet de Sivry-Houle <martin.poinsinet.de.sivry@gmail.com>
License: MIT License
Project-URL: Homepage, https://github.com/MartinPdeS/FlowCyPy
Project-URL: Documentation, https://martinpdes.github.io/FlowCyPy/
Project-URL: Repository, https://github.com/MartinPdeS/FlowCyPy.git
Keywords: refracive index,optics,microbeads,Mie scattering
Classifier: Programming Language :: Python
Classifier: Programming Language :: Python :: 3
Classifier: Programming Language :: Python :: Implementation :: CPython
Classifier: Development Status :: 3 - Alpha
Classifier: Topic :: Scientific/Engineering :: Physics
Classifier: License :: OSI Approved :: MIT License
Classifier: Intended Audience :: Science/Research
Requires-Python: >=3.10
License-File: LICENSE
Requires-Dist: pandas~=2.2
Requires-Dist: pint-pandas~=0.6
Requires-Dist: reportlab~=4.2
Requires-Dist: seaborn~=0.13
Requires-Dist: pydantic~=2.9
Requires-Dist: tabulate~=0.9
Requires-Dist: numpy<3.0,>=1.26
Requires-Dist: pint~=0.24
Requires-Dist: scipy~=1.14
Requires-Dist: PyMieSim
Requires-Dist: MPSPlots
Provides-Extra: testing
Requires-Dist: pytest>=0.6; extra == "testing"
Requires-Dist: pytest-cov>=2.0; extra == "testing"
Requires-Dist: pytest-json-report==1.5.0; extra == "testing"
Requires-Dist: coverage==7.6.7; extra == "testing"
Provides-Extra: documentation
Requires-Dist: numpydoc==1.8.0; extra == "documentation"
Requires-Dist: sphinx>=5.1.1; extra == "documentation"
Requires-Dist: sphinx-rtd-theme==3.0.2; extra == "documentation"
Requires-Dist: sphinx-gallery==0.18.0; extra == "documentation"
Requires-Dist: pydata-sphinx-theme==0.16.0; extra == "documentation"
Provides-Extra: dev
Requires-Dist: flake8==7.1.1; extra == "dev"
